NiukeBDuanChanpinJingliQiuzhiGonglve20212022Fix1/README.md
NiukeBDuanChanpinJingliQiuzhiGonglve20212022Fix1/__init__.py
NiukeBDuanChanpinJingliQiuzhiGonglve20212022Fix1/__main__.py
NiukeBDuanChanpinJingliQiuzhiGonglve20212022Fix1/file.epub
NiukeBDuanChanpinJingliQiuzhiGonglve20212022Fix1/index.html
NiukeBDuanChanpinJingliQiuzhiGonglve20212022Fix1/css/__init__.py
NiukeBDuanChanpinJingliQiuzhiGonglve20212022Fix1/css/annotations.css
NiukeBDuanChanpinJingliQiuzhiGonglve20212022Fix1/css/main.css
NiukeBDuanChanpinJingliQiuzhiGonglve20212022Fix1/css/normalize.css
NiukeBDuanChanpinJingliQiuzhiGonglve20212022Fix1/css/popup.css
NiukeBDuanChanpinJingliQiuzhiGonglve20212022Fix1/font/__init__.py
NiukeBDuanChanpinJingliQiuzhiGonglve20212022Fix1/font/fontello.eot
NiukeBDuanChanpinJingliQiuzhiGonglve20212022Fix1/font/fontello.svg
NiukeBDuanChanpinJingliQiuzhiGonglve20212022Fix1/font/fontello.ttf
NiukeBDuanChanpinJingliQiuzhiGonglve20212022Fix1/font/fontello.woff
NiukeBDuanChanpinJingliQiuzhiGonglve20212022Fix1/img/__init__.py
NiukeBDuanChanpinJingliQiuzhiGonglve20212022Fix1/img/annotator-glyph-sprite.png
NiukeBDuanChanpinJingliQiuzhiGonglve20212022Fix1/img/annotator-icon-sprite.png
NiukeBDuanChanpinJingliQiuzhiGonglve20212022Fix1/img/apple-touch-icon.png
NiukeBDuanChanpinJingliQiuzhiGonglve20212022Fix1/img/cancelfullscreen.png
NiukeBDuanChanpinJingliQiuzhiGonglve20212022Fix1/img/close.png
NiukeBDuanChanpinJingliQiuzhiGonglve20212022Fix1/img/fullscreen.png
NiukeBDuanChanpinJingliQiuzhiGonglve20212022Fix1/img/loader.gif
NiukeBDuanChanpinJingliQiuzhiGonglve20212022Fix1/img/menu-icon.png
NiukeBDuanChanpinJingliQiuzhiGonglve20212022Fix1/img/save.png
NiukeBDuanChanpinJingliQiuzhiGonglve20212022Fix1/img/saved.png
NiukeBDuanChanpinJingliQiuzhiGonglve20212022Fix1/img/settings-s.png
NiukeBDuanChanpinJingliQiuzhiGonglve20212022Fix1/img/settings.png
NiukeBDuanChanpinJingliQiuzhiGonglve20212022Fix1/img/star.png
NiukeBDuanChanpinJingliQiuzhiGonglve20212022Fix1/js/__init__.py
niuke_b_duan_chanpin_jingli_qiuzhi_gonglve_2021_2022_fix1-2025.3.25.0.dist-info/METADATA
niuke_b_duan_chanpin_jingli_qiuzhi_gonglve_2021_2022_fix1-2025.3.25.0.dist-info/WHEEL
niuke_b_duan_chanpin_jingli_qiuzhi_gonglve_2021_2022_fix1-2025.3.25.0.dist-info/entry_points.txt
niuke_b_duan_chanpin_jingli_qiuzhi_gonglve_2021_2022_fix1-2025.3.25.0.dist-info/top_level.txt
niuke_b_duan_chanpin_jingli_qiuzhi_gonglve_2021_2022_fix1-2025.3.25.0.dist-info/RECORD
